{
  "ImageWidth":"5376.0",
  "FocalLength":"1.3 mm",
  "Model":"RICOH THETA S",
  "ExposureTime":"1/6400",
  "Copyright":null,
  "Make":"RICOH",
  "ModifyDate":"2015:05:18 15:02:04",
  "ImageSize":"5376x2688",
  "ExposureMode":"Auto",
  "MaxApertureValue":"2.0",
  "ColorSpace":"sRGB",
  "SensitivityType":"Standard Output Sensitivity",
  "BrightnessValue":"10.3",
  "ExposureProgram":"Auto",
  "DateTimeOriginal":"2015:05:18 15:02:04",
  "ImageHeight":"2688.0",
  "CreateDate":"2015:05:18 15:02:04",
  "ImageDescription":"                                                               ",
  "WhiteBalance":"Auto",
  "FNumber":"2.0",
  "Flash":"No Flash",
  "ISO":"100.0",
  "Orientation":"Horizontal (normal)",
  "MeteringMode":"Multi-segment",
  "LightSource":"Unknown",
  "ApertureValue":"2.0",
  "Software":"RICOH THETA S",
  "GPSLatitudeRef":"North",
  "GPSLatitude":"+35.894469",
  "GPSLongitudeRef":"East",
  "GPSLongitude":"+137.433050",
  "GPSAltitudeRef":"Above Sea Level",
  "GPSAltitude":"830.3 m Above Sea Level",
  "GPSTimeStamp":"16:03:59"
}
